rotalabs_accel/__init__.py
rotalabs_accel/_version.py
rotalabs_accel/kernels/__init__.py
rotalabs_accel/kernels/activations.py
rotalabs_accel/kernels/gemm.py
rotalabs_accel/kernels/normalization.py
rotalabs_accel/kernels/quantization.py
rotalabs_accel/kernels/quantized_matmul.py
rotalabs_accel/kernels/rmsnorm.py
rotalabs_accel/kernels/rope.py
rotalabs_accel/kernels/swiglu.py
rotalabs_accel/modules/__init__.py
rotalabs_accel/quantization/__init__.py
rotalabs_accel/quantization/symmetric.py
rotalabs_accel/speculative/__init__.py
rotalabs_accel/speculative/config.py
rotalabs_accel/speculative/core.py
rotalabs_accel/speculative/eagle.py
rotalabs_accel/speculative/kv_compression.py
rotalabs_accel/speculative/medusa.py
rotalabs_accel/speculative/sampling.py
rotalabs_accel/speculative/tree.py
rotalabs_accel/utils/__init__.py
rotalabs_accel/utils/device.py
rotalabs_accel-1.0.0.dist-info/METADATA
rotalabs_accel-1.0.0.dist-info/WHEEL
rotalabs_accel-1.0.0.dist-info/licenses/LICENSE
rotalabs_accel-1.0.0.dist-info/RECORD
