Metadata-Version: 2.4
Name: rotalabs-accel
Version: 1.0.0
Summary: High-performance inference acceleration with Triton kernels, quantization, and speculative decoding
Project-URL: Homepage, https://rotalabs.ai
Project-URL: Repository, https://github.com/rotalabs/rotalabs-accel
Project-URL: Documentation, https://rotalabs.github.io/rotalabs-accel/
Author-email: Subhadip Mitra <subhadip@rotalabs.ai>, Rotalabs Research <research@rotalabs.ai>
License-Expression: AGPL-3.0-or-later
License-File: LICENSE
Keywords: acceleration,cuda,gpu,inference,llm,quantization,speculative-decoding,transformers,triton
Classifier: Development Status :: 4 - Beta
Classifier: Environment :: GPU :: NVIDIA CUDA
Classifier: Intended Audience :: Developers
Classifier: Intended Audience :: Science/Research
Classifier: License :: OSI Approved :: GNU Affero General Public License v3 or later (AGPLv3+)
Classifier: Programming Language :: Python :: 3
Classifier: Programming Language :: Python :: 3.9
Classifier: Programming Language :: Python :: 3.10
Classifier: Programming Language :: Python :: 3.11
Classifier: Programming Language :: Python :: 3.12
Classifier: Topic :: Scientific/Engineering :: Artificial Intelligence
Requires-Python: >=3.9
Requires-Dist: numpy>=1.24.0
Requires-Dist: torch>=2.0.0
Requires-Dist: transformers>=4.35.0
Provides-Extra: all
Requires-Dist: matplotlib>=3.7.0; extra == 'all'
Requires-Dist: pandas>=2.0.0; extra == 'all'
Requires-Dist: tqdm>=4.65.0; extra == 'all'
Requires-Dist: triton>=2.1.0; extra == 'all'
Provides-Extra: benchmark
Requires-Dist: matplotlib>=3.7.0; extra == 'benchmark'
Requires-Dist: pandas>=2.0.0; extra == 'benchmark'
Requires-Dist: tqdm>=4.65.0; extra == 'benchmark'
Provides-Extra: dev
Requires-Dist: mypy>=1.5.0; extra == 'dev'
Requires-Dist: pytest-benchmark>=4.0.0; extra == 'dev'
Requires-Dist: pytest>=7.4.0; extra == 'dev'
Requires-Dist: ruff>=0.1.0; extra == 'dev'
Provides-Extra: docs
Requires-Dist: mkdocs-material>=9.4.0; extra == 'docs'
Requires-Dist: mkdocs>=1.5.0; extra == 'docs'
Requires-Dist: mkdocstrings[python]>=0.24.0; extra == 'docs'
Provides-Extra: triton
Requires-Dist: triton>=2.1.0; extra == 'triton'
